CHANGES.txt
LICENSE.txt
MANIFEST.in
README.txt
run.ini
setup.py
wsgioauth/__init__.py
wsgioauth.zodb.egg-info/PKG-INFO
wsgioauth.zodb.egg-info/SOURCES.txt
wsgioauth.zodb.egg-info/dependency_links.txt
wsgioauth.zodb.egg-info/entry_points.txt
wsgioauth.zodb.egg-info/namespace_packages.txt
wsgioauth.zodb.egg-info/not-zip-safe
wsgioauth.zodb.egg-info/requires.txt
wsgioauth.zodb.egg-info/top_level.txt
wsgioauth/zodb/__init__.py