Metadata-Version: 1.0
Name: wsgioauth.zodb
Version: 0.2
Summary: A package that implements OAuth with ZODB storage.
Home-page: http://weblion.psu.edu/
Author: Michael Mulich | WebLion Group, Penn State University
Author-email: support@weblion.psu.edu
License: GPL
Keywords: web wsgi oauth authentication authorization
Platform: UNKNOWN
Classifier: Development Status :: 3 - Alpha
Classifier: Programming Language :: Python
Classifier: Topic :: Security
Classifier: Topic :: Internet :: WWW/HTTP
Classifier: Topic :: Internet :: WWW/HTTP :: WSGI
Classifier: Topic :: Internet :: WWW/HTTP :: WSGI :: Application
Classifier: Topic :: Internet :: WWW/HTTP :: WSGI :: Middleware
Classifier: Framework :: ZODB
